svgpath2mpl.py
svgpath2mpl-1.0.0.dist-info/LICENSE
svgpath2mpl-1.0.0.dist-info/METADATA
svgpath2mpl-1.0.0.dist-info/WHEEL
svgpath2mpl-1.0.0.dist-info/top_level.txt
svgpath2mpl-1.0.0.dist-info/RECORD
