Metadata-Version: 1.1
Name: svgpath2mpl
Version: 1.0.0
Summary: SVG path parser for matplotlib
Home-page: https://github.com/nvictus/svgpath2mpl
Author: Nezar Abdennur
Author-email: nabdennur@gmail.com
License: BSD
Keywords: svg,path,matplotlib,plotting,visualization
Platform: UNKNOWN
Classifier: Development Status :: 5 - Production/Stable
Classifier: License :: OSI Approved :: BSD License
Classifier: Operating System :: OS Independent
Classifier: Topic :: Scientific/Engineering :: Visualization
Classifier: Programming Language :: Python
Classifier: Programming Language :: Python :: 2.7
Classifier: Programming Language :: Python :: 3
